{"type":"FeatureCollection","features":[{"type":"Feature","geometry":{"type":"Point","coordinates":["-3.6892","41.6704"]},"properties":{"state":"SYMPTOMS"}},{"type":"Feature","geometry":{"type":"Point","coordinates":["-0.55","39.6"]},"properties":{"state":"HEALTHY"}},{"type":"Feature","geometry":{"type":"Point","coordinates":["-0.55","39.6"]},"properties":{"state":"HEALTHY"}},{"type":"Feature","geometry":{"type":"Point","coordinates":["-5.638","43.2875"]},"properties":{"state":"HEALTHY"}},{"type":"Feature","geometry":{"type":"Point","coordinates":["-1.0687","37.6907"]},"properties":{"state":"HEALTHY"}},{"type":"Feature","geometry":{"type":"Point","coordinates":["-1.0687","37.6907"]},"properties":{"state":"HEALTHY"}},{"type":"Feature","geometry":{"type":"Point","coordinates":["-0.5255","38.3964"]},"properties":{"state":"SYMPTOMS"}},{"type":"Feature","geometry":{"type":"Point","coordinates":["-0.5255","38.3964"]},"properties":{"state":"SYMPTOMS"}},{"type":"Feature","geometry":{"type":"Point","coordinates":["-0.4512","38.55"]},"properties":{"state":"HEALTHY"}},{"type":"Feature","geometry":{"type":"Point","coordinates":["-0.4512","38.55"]},"properties":{"state":"HEALTHY"}},{"type":"Feature","geometry":{"type":"Point","coordinates":["-0.4512","38.55"]},"properties":{"state":"HEALTHY"}},{"type":"Feature","geometry":{"type":"Point","coordinates":["-1.2564","37.5614"]},"properties":{"state":"HEALTHY"}},{"type":"Feature","geometry":{"type":"Point","coordinates":["-1.8564","38.9942"]},"properties":{"state":"SYMPTOMS"}},{"type":"Feature","geometry":{"type":"Point","coordinates":["-0.4512","38.55"]},"properties":{"state":"HEALTHY"}},{"type":"Feature","geometry":{"type":"Point","coordinates":["-0.2335","38.5075"]},"properties":{"state":"HEALTHY"}},{"type":"Feature","geometry":{"type":"Point","coordinates":["-0.5255","38.3964"]},"properties":{"state":"HEALTHY"}},{"type":"Feature","geometry":{"type":"Point","coordinates":["-0.5255","38.3964"]},"properties":{"state":"HEALTHY"}},{"type":"Feature","geometry":{"type":"Point","coordinates":["-0.5255","38.3964"]},"properties":{"state":"HEALTHY"}},{"type":"Feature","geometry":{"type":"Point","coordinates":["-0.5255","38.3964"]},"properties":{"state":"HEALTHY"}},{"type":"Feature","geometry":{"type":"Point","coordinates":["-0.5255","38.3964"]},"properties":{"state":"HEALTHY"}},{"type":"Feature","geometry":{"type":"Point","coordinates":["-2.5723","36.8141"]},"properties":{"state":"HEALTHY"}},{"type":"Feature","geometry":{"type":"Point","coordinates":["-0.5255","38.3964"]},"properties":{"state":"HEALTHY"}},{"type":"Feature","geometry":{"type":"Point","coordinates":["-3.7026","40.4165"]},"properties":{"state":"HEALTHY"}},{"type":"Feature","geometry":{"type":"Point","coordinates":["-3.7026","40.4165"]},"properties":{"state":"HEALTHY"}},{"type":"Feature","geometry":{"type":"Point","coordinates":["-3.7026","40.4165"]},"properties":{"state":"HEALTHY"}},{"type":"Feature","geometry":{"type":"Point","coordinates":["2.1925","41.4301"]},"properties":{"state":"SYMPTOMS"}},{"type":"Feature","geometry":{"type":"Point","coordinates":["-15.6808","27.7565"]},"properties":{"state":"SYMPTOMS"}},{"type":"Feature","geometry":{"type":"Point","coordinates":["-3.1333","43.2333"]},"properties":{"state":"HEALTHY"}},{"type":"Feature","geometry":{"type":"Point","coordinates":["-3.1333","43.2333"]},"properties":{"state":"HEALTHY"}},{"type":"Feature","geometry":{"type":"Point","coordinates":["-4.0226","39.8581"]},"properties":{"state":"HEALTHY"}}]}
